bitmex_simple_websocket.py
bitmex_simple_websocket-0.1.1.dist-info/DESCRIPTION.rst
bitmex_simple_websocket-0.1.1.dist-info/METADATA
bitmex_simple_websocket-0.1.1.dist-info/RECORD
bitmex_simple_websocket-0.1.1.dist-info/WHEEL
bitmex_simple_websocket-0.1.1.dist-info/metadata.json
bitmex_simple_websocket-0.1.1.dist-info/top_level.txt
