Metadata-Version: 2.0
Name: bitmex-simple-websocket
Version: 0.1.1
Summary: BitMEX simple websocket client
Home-page: https://github.com/qLethon/bitmex_simple_websocket
Author: qLethon
Author-email: qLethon@gmail.com
License: MIT
Platform: UNKNOWN
Requires-Dist: websocket-client (==0.46.0)
